actionai_mcp/__init__.py
actionai_mcp/__main__.py
actionai_mcp/client.py
actionai_mcp-1.0.0.dist-info/METADATA
actionai_mcp-1.0.0.dist-info/WHEEL
actionai_mcp-1.0.0.dist-info/entry_points.txt
actionai_mcp-1.0.0.dist-info/RECORD
