Metadata-Version: 2.4
Name: actionai-mcp
Version: 1.0.0
Summary: ActionAI MCP HTTP client for Claude Desktop and other MCP-compatible applications
Project-URL: Homepage, https://github.com/your-org/actionai-mcp-client
Project-URL: Repository, https://github.com/your-org/actionai-mcp-client.git
Project-URL: Issues, https://github.com/your-org/actionai-mcp-client/issues
Author-email: ActionAI Team <support@actionai.com>
License-Expression: MIT
Keywords: actionai,ai,assistant,claude,mcp,model-context-protocol
Classifier: Development Status :: 4 - Beta
Classifier: Intended Audience :: Developers
Classifier: License :: OSI Approved :: MIT License
Classifier: Programming Language :: Python :: 3
Classifier: Programming Language :: Python :: 3.8
Classifier: Programming Language :: Python :: 3.9
Classifier: Programming Language :: Python :: 3.10
Classifier: Programming Language :: Python :: 3.11
Classifier: Programming Language :: Python :: 3.12
Requires-Python: >=3.8
Requires-Dist: aiohttp>=3.8.0
